understory/__init__.py
understory/static/utils.js
understory/templates/__init__.py
understory/templates/home.html
understory/templates/template.html
understory-0.22.4.dist-info/METADATA
understory-0.22.4.dist-info/entry_points.txt
understory-0.22.4.dist-info/WHEEL
understory-0.22.4.dist-info/RECORD
